{"CfIpCountry": {"legend": ["SG", "GB", "VN", "XX", "HK", "ES", "FR", "NL", "MX", "CA", "IN", "TW", "TH", "BG", "IT", "CN", "KR", "DE", "ID", "JP", "UA", "RU", "US"], "series": [{"name": "SG", "value": 80}, {"name": "GB", "value": 218}, {"name": "VN", "value": 4}, {"name": "XX", "value": 6}, {"name": "HK", "value": 555}, {"name": "ES", "value": 6}, {"name": "FR", "value": 9}, {"name": "NL", "value": 8}, {"name": "MX", "value": 7}, {"name": "CA", "value": 1}, {"name": "IN", "value": 3}, {"name": "TW", "value": 39}, {"name": "TH", "value": 3}, {"name": "BG", "value": 17}, {"name": "IT", "value": 6}, {"name": "CN", "value": 2893}, {"name": "KR", "value": 10}, {"name": "DE", "value": 43}, {"name": "ID", "value": 1}, {"name": "JP", "value": 116}, {"name": "UA", "value": 6}, {"name": "RU", "value": 67}, {"name": "US", "value": 1790}]}, "TlsVersion": {"legend": ["TLSv1", "TLSv1.2", "TLSv1.3"], "series": [{"name": "TLSv1", "value": 109}, {"name": "TLSv1.2", "value": 722}, {"name": "TLSv1.3", "value": 5052}]}, "Hours": {"legend": [0, 1, 2, 3, 4, 5, 6, 7, 8, 9, 10, 11, 12, 13, 14, 15, 16, 17, 18, 19, 20, 21, 22, 23], "series": [{"name": 0, "value": 183}, {"name": 1, "value": 100}, {"name": 2, "value": 73}, {"name": 3, "value": 86}, {"name": 4, "value": 70}, {"name": 5, "value": 906}, {"name": 6, "value": 176}, {"name": 7, "value": 82}, {"name": 8, "value": 133}, {"name": 9, "value": 368}, {"name": 10, "value": 338}, {"name": 11, "value": 239}, {"name": 12, "value": 276}, {"name": 13, "value": 287}, {"name": 14, "value": 220}, {"name": 15, "value": 326}, {"name": 16, "value": 399}, {"name": 17, "value": 321}, {"name": 18, "value": 236}, {"name": 19, "value": 240}, {"name": 20, "value": 243}, {"name": 21, "value": 244}, {"name": 22, "value": 208}, {"name": 23, "value": 151}]}, "ScreenSize": {"legend": ["2048x1152", "384x792", "1536x960", "800x600", "1280x720", "360x800", "360x748", "424x918", "1475x830", "432x864", "385x833", "1366x768", "412x846", "1707x1067", "1440x960", "393x851", "375x667", "393x818", "1600x900", "1500x1000", "1920x980", "1920x1200", "414x896", "768x1024", "393x786", "1440x900", "2560x1440", "2195x1235", "534x854", "360x780", "3440x1440", "412x915", "1792x1120", "1463x915", "1224x816", "1494x934", "1680x1050", "390x844", "1280x1024", "491x1064", "444x960", "1080x1920", "1504x1003", "375x812", "1280x800", "1600x899", "1728x972", "1536x864", "360x640", "1494x935", "363x797", "393x873", "1372x858", "400x882", "396x823", "428x926", "1715x965", "1549x872", "1920x1080"], "series": [{"name": "2048x1152", "value": 7}, {"name": "384x792", "value": 1}, {"name": "1536x960", "value": 2}, {"name": "800x600", "value": 37}, {"name": "1280x720", "value": 29}, {"name": "360x800", "value": 4}, {"name": "360x748", "value": 3}, {"name": "424x918", "value": 7}, {"name": "1475x830", "value": 1}, {"name": "432x864", "value": 4}, {"name": "385x833", "value": 1}, {"name": "1366x768", "value": 11}, {"name": "412x846", "value": 5}, {"name": "1707x1067", "value": 1}, {"name": "1440x960", "value": 9}, {"name": "393x851", "value": 1}, {"name": "375x667", "value": 2}, {"name": "393x818", "value": 1}, {"name": "1600x900", "value": 11}, {"name": "1500x1000", "value": 3}, {"name": "1920x980", "value": 1}, {"name": "1920x1200", "value": 11}, {"name": "414x896", "value": 11}, {"name": "768x1024", "value": 1}, {"name": "393x786", "value": 1}, {"name": "1440x900", "value": 115}, {"name": "2560x1440", "value": 22}, {"name": "2195x1235", "value": 4}, {"name": "534x854", "value": 1}, {"name": "360x780", "value": 4}, {"name": "3440x1440", "value": 1}, {"name": "412x915", "value": 4}, {"name": "1792x1120", "value": 4}, {"name": "1463x915", "value": 4}, {"name": "1224x816", "value": 4}, {"name": "1494x934", "value": 11}, {"name": "1680x1050", "value": 21}, {"name": "390x844", "value": 4}, {"name": "1280x1024", "value": 1}, {"name": "491x1064", "value": 1}, {"name": "444x960", "value": 2}, {"name": "1080x1920", "value": 2}, {"name": "1504x1003", "value": 1}, {"name": "375x812", "value": 1}, {"name": "1280x800", "value": 3}, {"name": "1600x899", "value": 1}, {"name": "1728x972", "value": 1}, {"name": "1536x864", "value": 291}, {"name": "360x640", "value": 35}, {"name": "1494x935", "value": 2}, {"name": "363x797", "value": 1}, {"name": "393x873", "value": 12}, {"name": "1372x858", "value": 1}, {"name": "400x882", "value": 1}, {"name": "396x823", "value": 1}, {"name": "428x926", "value": 1}, {"name": "1715x965", "value": 1}, {"name": "1549x872", "value": 12}, {"name": "1920x1080", "value": 295}]}, "DisplaySize": {"legend": ["1872x992", "1920x943", "990x1083", "1536x753", "1920x881", "414x829", "1536x745", "1440x847", "1920x929", "1680x836", "412x826", "1440x821", "1536x722", "1475x687", "1680x842", "1032x1819", "1536x318", "2133x1002", "1600x828", "360x518", "1536x216", "1440x757", "1536x374", "1536x198", "360x714", "1264x708", "1709x892", "360x723", "1440x751", "1920x1001", "1536x156", "360x644", "1536x748", "390x664", "360x653", "1536x470", "393x711", "1536x351", "1536x754", "1920x891", "1441x912", "360x472", "1920x913", "1600x762", "1920x909", "1920x947", "1920x908", "1920x961", "1280x664", "1372x710", "2048x1022", "1324x945", "1164x855", "1536x278", "1440x734", "1024x569", "1920x928", "393x781", "1005x608", "412x753", "1456x891", "424x876", "1440x764", "1024x653", "1496x762", "1920x968", "414x767", "1600x732", "393x732", "375x551", "1536x763", "1741x885", "1440x788", "1536x487", "360x660", "1440x436", "1440x715", "1580x938", "534x814", "1536x434", "1536x388", "1920x946", "1920x976", "396x776", "566x616", "958x951", "1366x568", "1407x757", "1536x698", "1440x702", "796x1280", "1494x781", "393x755", "1494x791", "2560x1297", "360x722", "1544x832", "1536x631", "1920x927", "1745x861", "1920x980", "1324x744", "360x543", "2048x1010", "1536x778", "1904x935", "363x651", "1536x163", "1536x759", "1536x227", "1463x716", "393x780", "1280x577", "2048x1042", "393x731", "1536x739", "1440x789", "1280x960", "1536x760", "1536x150", "1536x302", "1920x906", "1536x724", "1680x887", "375x812", "1792x1009", "1504x860", "1318x597", "384x692", "1920x1057", "444x833", "1550x738", "360x576", "428x860", "1280x609", "1536x243", "1050x932", "1536x339", "1280x616", "800x600", "1536x850", "1280x580", "606x791", "432x772", "1536x711", "1536x792", "1536x714", "393x724", "2160x1011", "360x665", "1324x712", "2195x1069", "1536x323", "412x812", "1994x975", "1491x719", "1440x759", "1680x906", "1920x919", "1536x746", "980x1845", "1440x730", "375x553", "1232x609", "1918x937", "1440x849", "1536x262", "1981x1218", "360x579", "1536x298", "1920x1007", "1376x1250", "1440x674", "1494x815", "1462x791", "1536x292", "393x695", "1480x912", "1536x730", "360x622", "2560x1329", "1920x937", "1280x800", "1409x663", "1366x624", "1707x916", "393x726", "2276x1157", "1536x226", "1440x827", "1440x704", "412x714", "1920x934", "1920x938", "1771x1207", "1500x881", "1465x1287", "1440x714", "1536x650", "1920x903", "1440x796", "414x715", "730x616", "1920x1008", "1536x731", "1920x921", "491x925", "1536x167", "1920x970", "1858x977", "1280x649", "1536x684", "1364x726", "1440x720", "1920x917", "1407x658", "2195x1116", "1324x650", "1440x707", "424x771", "1918x1009", "1536x428", "1593x775", "982x722", "1440x725", "1280x666", "1920x969", "1536x666", "1440x710", "800x397", "1440x794", "1807x871", "1366x637", "1380x796", "393x708", "1536x378", "1536x274", "1550x672", "1224x656", "1920x1066", "384x652", "1463x772", "1440x688", "1536x691", "1392x789", "1161x931", "1536x186", "360x524", "1550x720", "400x882", "1366x625", "1873x921", "1600x746"], "series": [{"name": "1872x992", "value": 1}, {"name": "1920x943", "value": 1}, {"name": "990x1083", "value": 1}, {"name": "1536x753", "value": 1}, {"name": "1920x881", "value": 7}, {"name": "414x829", "value": 3}, {"name": "1536x745", "value": 2}, {"name": "1440x847", "value": 3}, {"name": "1920x929", "value": 3}, {"name": "1680x836", "value": 1}, {"name": "412x826", "value": 1}, {"name": "1440x821", "value": 4}, {"name": "1536x722", "value": 99}, {"name": "1475x687", "value": 1}, {"name": "1680x842", "value": 13}, {"name": "1032x1819", "value": 2}, {"name": "1536x318", "value": 1}, {"name": "2133x1002", "value": 3}, {"name": "1600x828", "value": 1}, {"name": "360x518", "value": 1}, {"name": "1536x216", "value": 12}, {"name": "1440x757", "value": 1}, {"name": "1536x374", "value": 2}, {"name": "1536x198", "value": 2}, {"name": "360x714", "value": 2}, {"name": "1264x708", "value": 1}, {"name": "1709x892", "value": 1}, {"name": "360x723", "value": 1}, {"name": "1440x751", "value": 3}, {"name": "1920x1001", "value": 1}, {"name": "1536x156", "value": 1}, {"name": "360x644", "value": 1}, {"name": "1536x748", "value": 1}, {"name": "390x664", "value": 4}, {"name": "360x653", "value": 1}, {"name": "1536x470", "value": 3}, {"name": "393x711", "value": 1}, {"name": "1536x351", "value": 30}, {"name": "1536x754", "value": 21}, {"name": "1920x891", "value": 2}, {"name": "1441x912", "value": 1}, {"name": "360x472", "value": 23}, {"name": "1920x913", "value": 1}, {"name": "1600x762", "value": 1}, {"name": "1920x909", "value": 1}, {"name": "1920x947", "value": 17}, {"name": "1920x908", "value": 13}, {"name": "1920x961", "value": 9}, {"name": "1280x664", "value": 1}, {"name": "1372x710", "value": 1}, {"name": "2048x1022", "value": 3}, {"name": "1324x945", "value": 1}, {"name": "1164x855", "value": 2}, {"name": "1536x278", "value": 2}, {"name": "1440x734", "value": 10}, {"name": "1024x569", "value": 4}, {"name": "1920x928", "value": 12}, {"name": "393x781", "value": 3}, {"name": "1005x608", "value": 1}, {"name": "412x753", "value": 1}, {"name": "1456x891", "value": 1}, {"name": "424x876", "value": 4}, {"name": "1440x764", "value": 6}, {"name": "1024x653", "value": 1}, {"name": "1496x762", "value": 1}, {"name": "1920x968", "value": 2}, {"name": "414x767", "value": 1}, {"name": "1600x732", "value": 1}, {"name": "393x732", "value": 3}, {"name": "375x551", "value": 1}, {"name": "1536x763", "value": 11}, {"name": "1741x885", "value": 1}, {"name": "1440x788", "value": 2}, {"name": "1536x487", "value": 2}, {"name": "360x660", "value": 1}, {"name": "1440x436", "value": 1}, {"name": "1440x715", "value": 20}, {"name": "1580x938", "value": 1}, {"name": "534x814", "value": 1}, {"name": "1536x434", "value": 2}, {"name": "1536x388", "value": 1}, {"name": "1920x946", "value": 8}, {"name": "1920x976", "value": 3}, {"name": "396x776", "value": 1}, {"name": "566x616", "value": 2}, {"name": "958x951", "value": 2}, {"name": "1366x568", "value": 4}, {"name": "1407x757", "value": 2}, {"name": "1536x698", "value": 1}, {"name": "1440x702", "value": 1}, {"name": "796x1280", "value": 1}, {"name": "1494x781", "value": 4}, {"name": "393x755", "value": 1}, {"name": "1494x791", "value": 3}, {"name": "2560x1297", "value": 2}, {"name": "360x722", "value": 1}, {"name": "1544x832", "value": 1}, {"name": "1536x631", "value": 2}, {"name": "1920x927", "value": 6}, {"name": "1745x861", "value": 1}, {"name": "1920x980", "value": 1}, {"name": "1324x744", "value": 1}, {"name": "360x543", "value": 1}, {"name": "2048x1010", "value": 1}, {"name": "1536x778", "value": 3}, {"name": "1904x935", "value": 1}, {"name": "363x651", "value": 1}, {"name": "1536x163", "value": 1}, {"name": "1536x759", "value": 1}, {"name": "1536x227", "value": 1}, {"name": "1463x716", "value": 1}, {"name": "393x780", "value": 1}, {"name": "1280x577", "value": 13}, {"name": "2048x1042", "value": 1}, {"name": "393x731", "value": 1}, {"name": "1536x739", "value": 4}, {"name": "1440x789", "value": 2}, {"name": "1280x960", "value": 1}, {"name": "1536x760", "value": 2}, {"name": "1536x150", "value": 3}, {"name": "1536x302", "value": 2}, {"name": "1920x906", "value": 1}, {"name": "1536x724", "value": 3}, {"name": "1680x887", "value": 3}, {"name": "375x812", "value": 1}, {"name": "1792x1009", "value": 4}, {"name": "1504x860", "value": 1}, {"name": "1318x597", "value": 1}, {"name": "384x692", "value": 1}, {"name": "1920x1057", "value": 1}, {"name": "444x833", "value": 2}, {"name": "1550x738", "value": 1}, {"name": "360x576", "value": 7}, {"name": "428x860", "value": 1}, {"name": "1280x609", "value": 6}, {"name": "1536x243", "value": 1}, {"name": "1050x932", "value": 1}, {"name": "1536x339", "value": 10}, {"name": "1280x616", "value": 3}, {"name": "800x600", "value": 17}, {"name": "1536x850", "value": 2}, {"name": "1280x580", "value": 1}, {"name": "606x791", "value": 4}, {"name": "432x772", "value": 4}, {"name": "1536x711", "value": 9}, {"name": "1536x792", "value": 3}, {"name": "1536x714", "value": 3}, {"name": "393x724", "value": 1}, {"name": "2160x1011", "value": 2}, {"name": "360x665", "value": 2}, {"name": "1324x712", "value": 1}, {"name": "2195x1069", "value": 1}, {"name": "1536x323", "value": 1}, {"name": "412x812", "value": 2}, {"name": "1994x975", "value": 2}, {"name": "1491x719", "value": 1}, {"name": "1440x759", "value": 1}, {"name": "1680x906", "value": 3}, {"name": "1920x919", "value": 1}, {"name": "1536x746", "value": 7}, {"name": "980x1845", "value": 1}, {"name": "1440x730", "value": 2}, {"name": "375x553", "value": 1}, {"name": "1232x609", "value": 1}, {"name": "1918x937", "value": 1}, {"name": "1440x849", "value": 2}, {"name": "1536x262", "value": 1}, {"name": "1981x1218", "value": 1}, {"name": "360x579", "value": 1}, {"name": "1536x298", "value": 1}, {"name": "1920x1007", "value": 3}, {"name": "1376x1250", "value": 1}, {"name": "1440x674", "value": 1}, {"name": "1494x815", "value": 2}, {"name": "1462x791", "value": 1}, {"name": "1536x292", "value": 2}, {"name": "393x695", "value": 1}, {"name": "1480x912", "value": 2}, {"name": "1536x730", "value": 1}, {"name": "360x622", "value": 1}, {"name": "2560x1329", "value": 4}, {"name": "1920x937", "value": 148}, {"name": "1280x800", "value": 13}, {"name": "1409x663", "value": 2}, {"name": "1366x624", "value": 1}, {"name": "1707x916", "value": 1}, {"name": "393x726", "value": 1}, {"name": "2276x1157", "value": 1}, {"name": "1536x226", "value": 5}, {"name": "1440x827", "value": 4}, {"name": "1440x704", "value": 1}, {"name": "412x714", "value": 5}, {"name": "1920x934", "value": 1}, {"name": "1920x938", "value": 1}, {"name": "1771x1207", "value": 14}, {"name": "1500x881", "value": 3}, {"name": "1465x1287", "value": 1}, {"name": "1440x714", "value": 1}, {"name": "1536x650", "value": 2}, {"name": "1920x903", "value": 3}, {"name": "1440x796", "value": 1}, {"name": "414x715", "value": 7}, {"name": "730x616", "value": 2}, {"name": "1920x1008", "value": 1}, {"name": "1536x731", "value": 1}, {"name": "1920x921", "value": 1}, {"name": "491x925", "value": 1}, {"name": "1536x167", "value": 2}, {"name": "1920x970", "value": 2}, {"name": "1858x977", "value": 7}, {"name": "1280x649", "value": 1}, {"name": "1536x684", "value": 4}, {"name": "1364x726", "value": 1}, {"name": "1440x720", "value": 23}, {"name": "1920x917", "value": 1}, {"name": "1407x658", "value": 5}, {"name": "2195x1116", "value": 3}, {"name": "1324x650", "value": 2}, {"name": "1440x707", "value": 9}, {"name": "424x771", "value": 3}, {"name": "1918x1009", "value": 1}, {"name": "1536x428", "value": 1}, {"name": "1593x775", "value": 1}, {"name": "982x722", "value": 2}, {"name": "1440x725", "value": 2}, {"name": "1280x666", "value": 1}, {"name": "1920x969", "value": 18}, {"name": "1536x666", "value": 1}, {"name": "1440x710", "value": 2}, {"name": "800x397", "value": 1}, {"name": "1440x794", "value": 9}, {"name": "1807x871", "value": 1}, {"name": "1366x637", "value": 1}, {"name": "1380x796", "value": 1}, {"name": "393x708", "value": 1}, {"name": "1536x378", "value": 1}, {"name": "1536x274", "value": 4}, {"name": "1550x672", "value": 1}, {"name": "1224x656", "value": 4}, {"name": "1920x1066", "value": 8}, {"name": "384x652", "value": 1}, {"name": "1463x772", "value": 3}, {"name": "1440x688", "value": 1}, {"name": "1536x691", "value": 1}, {"name": "1392x789", "value": 5}, {"name": "1161x931", "value": 2}, {"name": "1536x186", "value": 1}, {"name": "360x524", "value": 3}, {"name": "1550x720", "value": 8}, {"name": "400x882", "value": 1}, {"name": "1366x625", "value": 3}, {"name": "1873x921", "value": 3}, {"name": "1600x746", "value": 5}]}, "Language": {"legend": ["vi-VN", "en-ca", "zh-cn", "es-MX", "ko-KR", "en-GB", "zh-CN", "zh-tw", "en-US", "th-TH", "en-us", "en"], "series": [{"name": "vi-VN", "value": 4}, {"name": "en-ca", "value": 1}, {"name": "zh-cn", "value": 18}, {"name": "es-MX", "value": 1}, {"name": "ko-KR", "value": 1}, {"name": "en-GB", "value": 1}, {"name": "zh-CN", "value": 913}, {"name": "zh-tw", "value": 2}, {"name": "en-US", "value": 83}, {"name": "th-TH", "value": 1}, {"name": "en-us", "value": 1}, {"name": "en", "value": 4}]}}